df_to_rs/__init__.py
df_to_rs-0.1.30.dist-info/LICENSE.txt
df_to_rs-0.1.30.dist-info/METADATA
df_to_rs-0.1.30.dist-info/WHEEL
df_to_rs-0.1.30.dist-info/top_level.txt
df_to_rs-0.1.30.dist-info/RECORD
