Metadata-Version: 2.1
Name: df-to-rs
Version: 0.1.30
Summary: A package to upload Pandas DataFrame to Redshift
Home-page: https://github.com/ankitgoel888/df_to_rs
Author: Ankit Goel
Author-email: ankitgoel888@gmail.com
Classifier: Programming Language :: Python :: 3
Classifier: License :: OSI Approved :: MIT License
Classifier: Operating System :: OS Independent
Requires-Python: >=3.6, <4.1
License-File: LICENSE.txt
Requires-Dist: boto3
Requires-Dist: pandas
Requires-Dist: psycopg2
